{
  "title": "Welcome to Us!",
  "rPhone": "702-505-1040",
  "rName": "Restarant Name",
  "rEmail": "fanse2@gmail.com",
  "rAddr1": "3400 S. Jones Blvd.",
  "rAddr2": "Las Vegas NV 89146",
  "youtube": "",
  "main_bg": "assets/img/hero-bg.jpg",
  "about_bg": "assets/img/about-bg.jpg",
  "about_pic": "assets/img/about.jpg",
  "menu_title": "Check Our Tasty Menu",
  "gallery_title": "Some photos from Our Restaurant!",
  "contact_title": "Contact Us!",
  "hour": {
    "Mon-Thr": "11AM - 10PM",
    "Fri-Sat": "11AM - 12AM",
    "Sun Day": "Closed"
  },
  "gall": [
    "assets/img/gallery/gallery-1.jpg",
    "assets/img/gallery/gallery-2.jpg",
    "assets/img/gallery/gallery-3.jpg",
    "assets/img/gallery/gallery-4.jpg",
    "assets/img/gallery/gallery-5.jpg",
    "assets/img/gallery/gallery-6.jpg",
    "assets/img/gallery/gallery-7.jpg",
    "assets/img/gallery/gallery-8.jpg"
  ]
}
